django_listfilter_media_extension/__init__.py
django_listfilter_media_extension/admin.py
django_listfilter_media_extension/apps.py
django_listfilter_media_extension/constants.py
django_listfilter_media_extension/models.py
django_listfilter_media_extension/tests.py
django_listfilter_media_extension/views.py
django_listfilter_media_extension/migrations/__init__.py
django_listfilter_media_extension-0.1.1.dist-info/LICENSE
django_listfilter_media_extension-0.1.1.dist-info/METADATA
django_listfilter_media_extension-0.1.1.dist-info/WHEEL
django_listfilter_media_extension-0.1.1.dist-info/top_level.txt
django_listfilter_media_extension-0.1.1.dist-info/RECORD
