Metadata-Version: 2.1
Name: django-listfilter-media-extension
Version: 0.1.1
Summary: 为`listfilter`类添加`class Media`支持。
Home-page: UNKNOWN
Author: Che XiaoBo
Maintainer: Che XiaoBo
License: MIT
Keywords: django admin extentions,django listfilter media extension
Platform: UNKNOWN
Classifier: Development Status :: 5 - Production/Stable
Classifier: Intended Audience :: Developers
Classifier: Topic :: Software Development :: Libraries :: Python Modules
Classifier: License :: OSI Approved :: MIT License
Classifier: Programming Language :: Python :: 3
Classifier: Programming Language :: Python :: 3 :: Only
License-File: LICENSE
Requires-Dist: django
Requires-Dist: django-middleware-global-request
